LICENSE
MANIFEST.in
README.md
setup.py
fastaccesslimiter/README.md
fastaccesslimiter/__init__.py
fastaccesslimiter/compat.py
fastaccesslimiter/fastaccesslimiter.py
fastaccesslimiter/fastaccesslimiter_min.py
fastaccesslimiter.egg-info/PKG-INFO
fastaccesslimiter.egg-info/SOURCES.txt
fastaccesslimiter.egg-info/dependency_links.txt
fastaccesslimiter.egg-info/not-zip-safe
fastaccesslimiter.egg-info/top_level.txt
tests/test_fastaccesslimiter.py
tests/test_unit.py